{
  "parent": "minecraft:recipes/root",
  "rewards": {
    "recipes": [
      "soulpowered:netherite_soul_amulet"
    ]
  },
  "criteria": {
    "has_diamond_soul_amulet": {
      "trigger": "minecraft:inventory_changed",
      "conditions": {
        "items": [
          {
            "item": "soulpowered:diamond_soul_amulet"
          }
        ]
      }
    },
    "has_netherite": {
      "trigger": "minecraft:inventory_changed",
      "conditions": {
        "items": [
          {
            "tag": "forge:ingots/netherite"
          }
        ]
      }
    },
    "has_the_recipe": {
      "trigger": "minecraft:recipe_unlocked",
      "conditions": {
        "recipe": "soulpowered:netherite_soul_amulet"
      }
    }
  },
  "requirements": [
    [
      "has_diamond_soul_amulet",
      "has_netherite",
      "has_the_recipe"
    ]
  ]
}